pygetpapers1/__init__.py
pygetpapers1/config.ini
pygetpapers1/download_tools.py
pygetpapers1/extensions.py
pygetpapers1/pgexceptions.py
pygetpapers1/pygetpapers1.py
pygetpapers1/repositoryinterface.py
pygetpapers1/repository/__init__.py
pygetpapers1/repository/arxiv.py
pygetpapers1/repository/crossref.py
pygetpapers1/repository/europe_pmc.py
pygetpapers1/repository/openalex.py
pygetpapers1/repository/rxiv.py
pygetpapers1/repository/rxivist.py
pygetpapers1-1.2.8.dist-info/licenses/LICENSE
pygetpapers1-1.2.8.dist-info/METADATA
pygetpapers1-1.2.8.dist-info/WHEEL
pygetpapers1-1.2.8.dist-info/entry_points.txt
pygetpapers1-1.2.8.dist-info/top_level.txt
pygetpapers1-1.2.8.dist-info/RECORD
