Metadata-Version: 2.4
Name: pygetpapers1
Version: 1.2.8
Summary: Automated Download of Research Papers from various scientific repositories
Home-page: https://github.com/petermr/pygetpapers
Author: Ayush Garg
Author-email: ayush@science.org.in
License: Apache License
Keywords: research automation
Classifier: Development Status :: 4 - Beta
Classifier: Intended Audience :: Developers
Classifier: License :: OSI Approved :: Apache Software License
Classifier: Natural Language :: English
Classifier: Programming Language :: Python :: 3.4
Classifier: Programming Language :: Python :: 3.5
Classifier: Programming Language :: Python :: 3.6
Classifier: Programming Language :: Python :: 3.7
Classifier: Programming Language :: Python :: 3.8
Classifier: Programming Language :: Python :: 3.9
Requires-Python: >=3.5
License-File: LICENSE
Requires-Dist: requests
Requires-Dist: pandas
Requires-Dist: lxml
Requires-Dist: xmltodict
Requires-Dist: configargparse
Requires-Dist: habanero
Requires-Dist: arxiv
Requires-Dist: dict2xml
Requires-Dist: tqdm
Requires-Dist: coloredlogs
Dynamic: author
Dynamic: author-email
Dynamic: classifier
Dynamic: description
Dynamic: description-content-type
Dynamic: home-page
Dynamic: keywords
Dynamic: license
Dynamic: license-file
Dynamic: requires-dist
Dynamic: requires-python
Dynamic: summary
